Metadata-Version: 2.1
Name: ducut
Version: 0.0.3
Summary: ducut
Home-page: https://github.com/Mywayking/
Author: galen
Author-email: mywayking@icloud.com
License: Apache-2.0
Keywords: word cut for du
Platform: UNKNOWN
Classifier: License :: OSI Approved :: Apache Software License
Classifier: Operating System :: OS Independent
Classifier: Intended Audience :: Developers
Classifier: Intended Audience :: Education
Classifier: Intended Audience :: Science/Research
Classifier: Programming Language :: Python :: 3
Classifier: Programming Language :: Python :: 3.5
Classifier: Programming Language :: Python :: 3.6
Classifier: Programming Language :: Python :: 3.7
Requires-Python: >=3.4
